{
    "manifest-version": 2,
    "name": "capell-app/foundation-theme",
    "kind": "theme",
    "capell-version": "^4.0",
    "productGroup": "Capell Foundation",
    "tier": "free",
    "bundle": "foundation",
    "description": "Foundation Theme provides the default Capell theme assets, Tailwind pipeline, Blade directives, and media handling.",
    "themeKey": "default",
    "extends": null,
    "surfaces": ["frontend", "admin"],
    "dependencies": {
        "requires": [],
        "optional": [],
        "conflicts": []
    },
    "lifecycle": {
        "activation": "manual",
        "defaultStatus": "available",
        "requiresInstallCommand": false
    },
    "providers": {
        "metadata": [],
        "install": [],
        "runtime": [
            "Capell\\FoundationTheme\\Providers\\FoundationThemeServiceProvider"
        ],
        "admin": [],
        "frontend": []
    },
    "database": {
        "migrations": false,
        "settings": true,
        "requiredTables": []
    },
    "commands": {
        "install": null,
        "setup": "capell:foundation-theme-setup",
        "setupParams": [],
        "demo": null,
        "demoParams": [],
        "health": null
    },
    "settings": [],
    "permissions": [],
    "capabilities": [],
    "assets": [],
    "healthChecks": []
}
